tcheasy/__init__.py
tcheasy/__main__.py
tcheasy/sort_parameters.py
tcheasy/type_check.py
tcheasy/version.py
tcheasy-1.1.0.dist-info/LICENSE
tcheasy-1.1.0.dist-info/METADATA
tcheasy-1.1.0.dist-info/WHEEL
tcheasy-1.1.0.dist-info/top_level.txt
tcheasy-1.1.0.dist-info/RECORD
