Metadata-Version: 2.1
Name: tcheasy
Version: 1.1.0
Summary: A python decorator which checks types & restrictions for user inputs
Home-page: https://github.com/No9005/tcheasy
Download-URL: https://github.com/No9005/tcheasy/archive/refs/tags/v.1.1.0.tar.gz
Author: Daniel Kiermeier
Author-email: d.kiermeier@layers-of-life.com
License: MIT
Platform: UNKNOWN
License-File: LICENSE
